[
  {
    "title": "Python + R Developer (bioinformatic), New Zealand",
    "link": "https://spb.hh.ru/vacancy/77394308?from=vacancy_search_list&query=python",
    "salary": "5 000 – 7 500 USD",
    "employer": "ГК ВИЗАВИ Консалт",
    "city": "Москва"
  },
  {
    "title": "Python + R Developer (bioinformatic), New Zealand",
    "link": "https://spb.hh.ru/vacancy/77400852?from=vacancy_search_list&query=python",
    "salary": "5 000 – 7 500 USD",
    "employer": "ГК ВИЗАВИ Консалт",
    "city": "Санкт-Петербург"
  },
  {
    "title": "Ведущий Python разработчик (удаленка)",
    "link": "https://spb.hh.ru/vacancy/76832091?from=vacancy_search_list&query=python",
    "salary": "до 8 000 USD",
    "employer": "Apostro",
    "city": "Москва"
  },
  {
    "title": "Team Lead Python",
    "link": "https://spb.hh.ru/vacancy/69431362?from=vacancy_search_list&query=python",
    "salary": "от 6 500 USD",
    "employer": "Дартс рекрутинг сервисез",
    "city": "Москва"
  },
  {
    "title": "Team Lead Python",
    "link": "https://spb.hh.ru/vacancy/69431361?from=vacancy_search_list&query=python",
    "salary": "от 6 500 USD",
    "employer": "Дартс рекрутинг сервисез",
    "city": "Санкт-Петербург"
  },
  {
    "title": "Преподаватель по программированию в онлайн-школе (Python в Minecraft)",
    "link": "https://spb.hh.ru/vacancy/76843216?from=vacancy_search_list&query=python",
    "salary": "300 – 800 USD",
    "employer": "ООО Айтигенио",
    "city": "Москва"
  },
  {
    "title": "Senior Python Developer",
    "link": "https://spb.hh.ru/vacancy/76650700?from=vacancy_search_list&query=python",
    "salary": "5 000 – 6 000 USD",
    "employer": "CLS Global",
    "city": "Москва"
  },
  {
    "title": "Senior Python Developer (remote)",
    "link": "https://spb.hh.ru/vacancy/77242773?from=vacancy_search_list&query=python",
    "salary": "от 3 500 USD",
    "employer": "LATOKEN",
    "city": "Москва"
  },
  {
    "title": "Игровой аналитик (Game/Business analyst)",
    "link": "https://spb.hh.ru/vacancy/76733632?from=vacancy_search_list&query=python",
    "salary": "1 400 – 2 000 USD",
    "employer": "Sidus Gates IT Services L.L.C",
    "city": "Москва"
  },
  {
    "title": "Data Analyst (middle/senior)",
    "link": "https://spb.hh.ru/vacancy/76866211?from=vacancy_search_list&query=python",
    "salary": "2 500 – 3 500 USD",
    "employer": "Fundraise Up",
    "city": "Москва"
  },
  {
    "title": "Senior Backend Engineer (Remote)",
    "link": "https://spb.hh.ru/vacancy/76522811?from=vacancy_search_list&query=python",
    "salary": "5 000 – 7 000 USD",
    "employer": "Truv Inc.",
    "city": "Москва"
  },
  {
    "title": "AWS DevOps Engineer (Middle/ Senior) Remote",
    "link": "https://spb.hh.ru/vacancy/76455750?from=vacancy_search_list&query=python",
    "salary": "4 000 – 5 000 USD",
    "employer": "Pixellu",
    "city": "Москва"
  },
  {
    "title": "CI Engineer",
    "link": "https://spb.hh.ru/vacancy/76770084?from=vacancy_search_list&query=python",
    "salary": "от 5 000 USD",
    "employer": "NetworkOptix",
    "city": "Москва"
  },
  {
    "title": "Senior DevOps Engineer",
    "link": "https://spb.hh.ru/vacancy/77382560?from=vacancy_search_list&query=python",
    "salary": "2 500 – 5 000 USD",
    "employer": "ARB",
    "city": "Москва"
  },
  {
    "title": "Senior DevOps Engineer (Serbia/Canada)",
    "link": "https://spb.hh.ru/vacancy/76541057?from=vacancy_search_list&query=python",
    "salary": "3 000 – 5 000 USD",
    "employer": "BookedBy",
    "city": "Москва"
  },
  {
    "title": "System engineer / Kubernetes Developer",
    "link": "https://spb.hh.ru/vacancy/76819153?from=vacancy_search_list&query=python",
    "salary": "от 5 500 USD",
    "employer": "NetworkOptix",
    "city": "Москва"
  }
]